is_numba.py
is_numba-1.0.0.dist-info/licenses/LICENSE
is_numba-1.0.0.dist-info/METADATA
is_numba-1.0.0.dist-info/WHEEL
is_numba-1.0.0.dist-info/top_level.txt
is_numba-1.0.0.dist-info/RECORD
