Metadata-Version: 2.4
Name: is_numba
Version: 1.0.0
Summary: Determine if a variable is a number. Not recommended for use
Author-email: Matthew Liepke <author@example.com>
License-Expression: AGPL-3.0-or-later
Project-URL: Homepage, https://github.com/mjliepke/is_numba
Project-URL: Issues, https://github.com/mjliepke/is_numba/issues
Classifier: Programming Language :: Python :: 3
Classifier: Operating System :: OS Independent
Requires-Python: >=3.9
License-File: LICENSE
Dynamic: license-file
